[
  {
    "symbol": "SNDK",
    "momentum": 1770.3091488901528,
    "currentPrice": 891.719970703125,
    "name": "Sandisk"
  },
  {
    "symbol": "LITE",
    "momentum": 1203.964757194259,
    "currentPrice": 824.010009765625,
    "name": "Lumentum"
  },
  {
    "symbol": "WDC",
    "momentum": 636.3906418510821,
    "currentPrice": 365.0,
    "name": "Western Digital"
  },
  {
    "symbol": "CIEN",
    "momentum": 483.57396641109426,
    "currentPrice": 475.760009765625,
    "name": "Ciena"
  },
  {
    "symbol": "MU",
    "momentum": 479.2017712824479,
    "currentPrice": 456.2300109863281,
    "name": "Micron Technology"
  },
  {
    "symbol": "STX",
    "momentum": 420.71130750561645,
    "currentPrice": 519.5999755859375,
    "name": "Seagate Technology"
  },
  {
    "symbol": "SATS",
    "momentum": 415.9728362489444,
    "currentPrice": 131.38999938964844,
    "name": "EchoStar"
  },
  {
    "symbol": "COHR",
    "momentum": 395.6897774026143,
    "currentPrice": 308.20001220703125,
    "name": "Coherent Corp."
  },
  {
    "symbol": "TER",
    "momentum": 330.48226758332027,
    "currentPrice": 364.9599914550781,
    "name": "Teradyne"
  },
  {
    "symbol": "FIX",
    "momentum": 310.60683909463484,
    "currentPrice": 1648.9599609375,
    "name": "Comfort Systems USA"
  },
  {
    "symbol": "GLW",
    "momentum": 256.1609074450034,
    "currentPrice": 168.27000427246094,
    "name": "Corning Inc."
  },
  {
    "symbol": "WBD",
    "momentum": 252.90404663756357,
    "currentPrice": 27.200000762939453,
    "name": "Warner Bros. Discovery"
  },
  {
    "symbol": "VRT",
    "momentum": 251.0547976196289,
    "currentPrice": 301.1600036621094,
    "name": "Vertiv"
  },
  {
    "symbol": "LRCX",
    "momentum": 244.83240065276627,
    "currentPrice": 265.1600036621094,
    "name": "Lam Research"
  },
  {
    "symbol": "ALB",
    "momentum": 225.05605778500274,
    "currentPrice": 185.3800048828125,
    "name": "Albemarle Corporation"
  },
  {
    "symbol": "AMAT",
    "momentum": 161.20592625701013,
    "currentPrice": 394.260009765625,
    "name": "Applied Materials"
  },
  {
    "symbol": "GEV",
    "momentum": 156.96291564336482,
    "currentPrice": 985.9199829101562,
    "name": "GE Vernova"
  },
  {
    "symbol": "CAT",
    "momentum": 155.75292322131585,
    "currentPrice": 770.1699829101562,
    "name": "Caterpillar Inc."
  },
  {
    "symbol": "TPR",
    "momentum": 152.51510623531348,
    "currentPrice": 151.3699951171875,
    "name": "Tapestry"
  },
  {
    "symbol": "INTC",
    "momentum": 137.0254961834181,
    "currentPrice": 64.94000244140625,
    "name": "Intel"
  },
  {
    "symbol": "KLAC",
    "momentum": 131.56702338633198,
    "currentPrice": 1748.1099853515625,
    "name": "KLA Corporation"
  },
  {
    "symbol": "MRNA",
    "momentum": 129.45612549278536,
    "currentPrice": 54.2599983215332,
    "name": "Moderna"
  },
  {
    "symbol": "AMD",
    "momentum": 128.87077271360772,
    "currentPrice": 258.1199951171875,
    "name": "Advanced Micro Devices"
  },
  {
    "symbol": "KEYS",
    "momentum": 123.25100409267029,
    "currentPrice": 325.25,
    "name": "Keysight Technologies"
  },
  {
    "symbol": "VLO",
    "momentum": 116.77558652694135,
    "currentPrice": 235.0,
    "name": "Valero Energy"
  },
  {
    "symbol": "NEM",
    "momentum": 116.12448254348978,
    "currentPrice": 113.04000091552734,
    "name": "Newmont"
  },
  {
    "symbol": "CHRW",
    "momentum": 114.56766980714366,
    "currentPrice": 168.0800018310547,
    "name": "C.H. Robinson"
  },
  {
    "symbol": "APA",
    "momentum": 112.79959239427448,
    "currentPrice": 36.599998474121094,
    "name": "APA Corporation"
  },
  {
    "symbol": "PWR",
    "momentum": 111.10252412440038,
    "currentPrice": 591.8200073242188,
    "name": "Quanta Services"
  },
  {
    "symbol": "MPWR",
    "momentum": 110.56315963505105,
    "currentPrice": 1353.0,
    "name": "Monolithic Power Systems"
  },
  {
    "symbol": "HWM",
    "momentum": 110.38375291780385,
    "currentPrice": 254.0399932861328,
    "name": "Howmet Aerospace"
  },
  {
    "symbol": "APP",
    "momentum": 110.09094586300301,
    "currentPrice": 464.6300048828125,
    "name": "AppLovin"
  },
  {
    "symbol": "CMI",
    "momentum": 108.41677775847458,
    "currentPrice": 601.4600219726562,
    "name": "Cummins"
  },
  {
    "symbol": "IVZ",
    "momentum": 108.02863812906855,
    "currentPrice": 24.709999084472656,
    "name": "Invesco"
  },
  {
    "symbol": "VTRS",
    "momentum": 106.56512442595985,
    "currentPrice": 13.859999656677246,
    "name": "Viatris"
  },
  {
    "symbol": "HII",
    "momentum": 106.48698148269908,
    "currentPrice": 398.1300048828125,
    "name": "Huntington Ingalls Industries"
  },
  {
    "symbol": "APH",
    "momentum": 105.99976962835787,
    "currentPrice": 146.97999572753906,
    "name": "Amphenol"
  },
  {
    "symbol": "HOOD",
    "momentum": 102.18888193061586,
    "currentPrice": 87.31999969482422,
    "name": "Robinhood Markets"
  },
  {
    "symbol": "GNRC",
    "momentum": 99.62945896389031,
    "currentPrice": 204.39999389648438,
    "name": "Generac"
  },
  {
    "symbol": "GOOGL",
    "momentum": 98.24372350748403,
    "currentPrice": 337.1199951171875,
    "name": "Alphabet Inc. (Class A)"
  },
  {
    "symbol": "DD",
    "momentum": 97.92926146611278,
    "currentPrice": 46.060001373291016,
    "name": "DuPont"
  },
  {
    "symbol": "ADI",
    "momentum": 97.07863755694765,
    "currentPrice": 347.94000244140625,
    "name": "Analog Devices"
  },
  {
    "symbol": "GOOG",
    "momentum": 95.68147625692231,
    "currentPrice": 334.4700012207031,
    "name": "Alphabet Inc. (Class C)"
  },
  {
    "symbol": "EME",
    "momentum": 94.14373823829443,
    "currentPrice": 803.6400146484375,
    "name": "Emcor"
  },
  {
    "symbol": "HAS",
    "momentum": 93.92703750214018,
    "currentPrice": 93.93000030517578,
    "name": "Hasbro"
  },
  {
    "symbol": "LUV",
    "momentum": 92.66088753677771,
    "currentPrice": 41.70000076293945,
    "name": "Southwest Airlines"
  },
  {
    "symbol": "FDX",
    "momentum": 92.10115138479037,
    "currentPrice": 364.9200134277344,
    "name": "FedEx"
  },
  {
    "symbol": "EL",
    "momentum": 91.39907271121578,
    "currentPrice": 76.5999984741211,
    "name": "Est\u00e9e Lauder Companies (The)"
  },
  {
    "symbol": "JBL",
    "momentum": 90.9150407157004,
    "currentPrice": 304.95001220703125,
    "name": "Jabil"
  },
  {
    "symbol": "JBHT",
    "momentum": 90.41692748056434,
    "currentPrice": 224.1699981689453,
    "name": "J.B. Hunt"
  },
  {
    "symbol": "MCHP",
    "momentum": 89.69787256069155,
    "currentPrice": 74.48999786376953,
    "name": "Microchip Technology"
  },
  {
    "symbol": "ULTA",
    "momentum": 89.17590142260853,
    "currentPrice": 539.1400146484375,
    "name": "Ulta Beauty"
  },
  {
    "symbol": "ANET",
    "momentum": 87.6026112124601,
    "currentPrice": 154.3300018310547,
    "name": "Arista Networks"
  },
  {
    "symbol": "GE",
    "momentum": 86.96175671154919,
    "currentPrice": 313.92999267578125,
    "name": "GE Aerospace"
  },
  {
    "symbol": "C",
    "momentum": 83.91922896016601,
    "currentPrice": 131.69000244140625,
    "name": "Citigroup"
  },
  {
    "symbol": "JCI",
    "momentum": 83.28782119123485,
    "currentPrice": 137.2100067138672,
    "name": "Johnson Controls"
  },
  {
    "symbol": "AVGO",
    "momentum": 82.94067085198506,
    "currentPrice": 396.7200012207031,
    "name": "Broadcom"
  },
  {
    "symbol": "ON",
    "momentum": 82.56933950159672,
    "currentPrice": 72.43000030517578,
    "name": "ON Semiconductor"
  },
  {
    "symbol": "MPC",
    "momentum": 81.75650423708319,
    "currentPrice": 223.02999877929688,
    "name": "Marathon Petroleum"
  },
  {
    "symbol": "DELL",
    "momentum": 79.73943192445547,
    "currentPrice": 177.27999877929688,
    "name": "Dell Technologies"
  },
  {
    "symbol": "RL",
    "momentum": 79.67012061043273,
    "currentPrice": 369.3599853515625,
    "name": "Ralph Lauren Corporation"
  },
  {
    "symbol": "LVS",
    "momentum": 79.65012967677761,
    "currentPrice": 56.2599983215332,
    "name": "Las Vegas Sands"
  },
  {
    "symbol": "GM",
    "momentum": 79.13172921103019,
    "currentPrice": 77.77999877929688,
    "name": "General Motors"
  },
  {
    "symbol": "PH",
    "momentum": 78.1973299167731,
    "currentPrice": 963.760009765625,
    "name": "Parker Hannifin"
  },
  {
    "symbol": "GS",
    "momentum": 77.38037627571123,
    "currentPrice": 899.489990234375,
    "name": "Goldman Sachs"
  },
  {
    "symbol": "PSX",
    "momentum": 76.83391788782615,
    "currentPrice": 161.44000244140625,
    "name": "Phillips 66"
  },
  {
    "symbol": "IBKR",
    "momentum": 76.07158387670755,
    "currentPrice": 79.69000244140625,
    "name": "Interactive Brokers"
  },
  {
    "symbol": "CFG",
    "momentum": 75.97608537718833,
    "currentPrice": 65.19000244140625,
    "name": "Citizens Financial Group"
  },
  {
    "symbol": "NVDA",
    "momentum": 75.20644715602067,
    "currentPrice": 198.8699951171875,
    "name": "Nvidia"
  },
  {
    "symbol": "DG",
    "momentum": 72.27894563902001,
    "currentPrice": 121.55999755859375,
    "name": "Dollar General"
  },
  {
    "symbol": "CRL",
    "momentum": 72.25899456216277,
    "currentPrice": 180.55999755859375,
    "name": "Charles River Laboratories"
  },
  {
    "symbol": "INCY",
    "momentum": 71.24545538584972,
    "currentPrice": 97.0999984741211,
    "name": "Incyte"
  },
  {
    "symbol": "LHX",
    "momentum": 70.76244854616047,
    "currentPrice": 355.9200134277344,
    "name": "L3Harris"
  },
  {
    "symbol": "ROK",
    "momentum": 70.6313622825154,
    "currentPrice": 397.3999938964844,
    "name": "Rockwell Automation"
  },
  {
    "symbol": "NTRS",
    "momentum": 69.15883410847054,
    "currentPrice": 156.07000732421875,
    "name": "Northern Trust"
  },
  {
    "symbol": "NRG",
    "momentum": 68.79438030166813,
    "currentPrice": 168.4499969482422,
    "name": "NRG Energy"
  },
  {
    "symbol": "TSLA",
    "momentum": 68.05630193033944,
    "currentPrice": 391.95001220703125,
    "name": "Tesla"
  },
  {
    "symbol": "CAH",
    "momentum": 67.57366442530011,
    "currentPrice": 211.8300018310547,
    "name": "Cardinal Health"
  },
  {
    "symbol": "STLD",
    "momentum": 67.1597193579126,
    "currentPrice": 194.11000061035156,
    "name": "Steel Dynamics"
  },
  {
    "symbol": "TEL",
    "momentum": 66.53072096325296,
    "currentPrice": 234.14999389648438,
    "name": "TE Connectivity"
  },
  {
    "symbol": "HCA",
    "momentum": 65.33435903500012,
    "currentPrice": 488.5799865722656,
    "name": "HCA Healthcare"
  },
  {
    "symbol": "PLTR",
    "momentum": 65.23568542140453,
    "currentPrice": 142.14999389648438,
    "name": "Palantir Technologies"
  },
  {
    "symbol": "HAL",
    "momentum": 65.06733920524375,
    "currentPrice": 37.540000915527344,
    "name": "Halliburton"
  },
  {
    "symbol": "BIIB",
    "momentum": 64.74976228040344,
    "currentPrice": 180.5399932861328,
    "name": "Biogen"
  },
  {
    "symbol": "RTX",
    "momentum": 64.29015739479166,
    "currentPrice": 198.38999938964844,
    "name": "RTX Corporation"
  },
  {
    "symbol": "JNJ",
    "momentum": 63.81944947591675,
    "currentPrice": 238.6699981689453,
    "name": "Johnson & Johnson"
  },
  {
    "symbol": "NUE",
    "momentum": 63.499520685180265,
    "currentPrice": 189.60000610351562,
    "name": "Nucor"
  },
  {
    "symbol": "BKR",
    "momentum": 62.898579925843315,
    "currentPrice": 60.06999969482422,
    "name": "Baker Hughes"
  },
  {
    "symbol": "STT",
    "momentum": 62.27783132067314,
    "currentPrice": 142.74000549316406,
    "name": "State Street Corporation"
  },
  {
    "symbol": "MRK",
    "momentum": 61.82695754943063,
    "currentPrice": 117.9000015258789,
    "name": "Merck & Co."
  },
  {
    "symbol": "NDSN",
    "momentum": 61.35414798047888,
    "currentPrice": 275.0,
    "name": "Nordson Corporation"
  },
  {
    "symbol": "IDXX",
    "momentum": 61.21576726854406,
    "currentPrice": 580.760009765625,
    "name": "Idexx Laboratories"
  },
  {
    "symbol": "DLTR",
    "momentum": 60.9752765303835,
    "currentPrice": 101.33000183105469,
    "name": "Dollar Tree"
  },
  {
    "symbol": "BK",
    "momentum": 59.62242258099357,
    "currentPrice": 131.9600067138672,
    "name": "BNY Mellon"
  },
  {
    "symbol": "MS",
    "momentum": 59.537462172123604,
    "currentPrice": 191.6199951171875,
    "name": "Morgan Stanley"
  },
  {
    "symbol": "DAL",
    "momentum": 59.18830447277731,
    "currentPrice": 71.98999786376953,
    "name": "Delta Air Lines"
  },
  {
    "symbol": "CSX",
    "momentum": 58.79852270696588,
    "currentPrice": 42.099998474121094,
    "name": "CSX Corporation"
  },
  {
    "symbol": "CEG",
    "momentum": 58.70132782727633,
    "currentPrice": 294.7300109863281,
    "name": "Constellation Energy"
  },
  {
    "symbol": "FSLR",
    "momentum": 58.6026761767274,
    "currentPrice": 195.1999969482422,
    "name": "First Solar"
  },
  {
    "symbol": "BEN",
    "momentum": 57.81337252189419,
    "currentPrice": 26.6299991607666,
    "name": "Franklin Resources"
  },
  {
    "symbol": "CCL",
    "momentum": 57.467683074202455,
    "currentPrice": 28.81999969482422,
    "name": "Carnival"
  },
  {
    "symbol": "HST",
    "momentum": 56.7289376291055,
    "currentPrice": 20.690000534057617,
    "name": "Host Hotels & Resorts"
  },
  {
    "symbol": "BG",
    "momentum": 55.22305514650725,
    "currentPrice": 120.0,
    "name": "Bunge Global"
  },
  {
    "symbol": "ROST",
    "momentum": 55.17224825298075,
    "currentPrice": 224.14999389648438,
    "name": "Ross Stores"
  },
  {
    "symbol": "MAR",
    "momentum": 54.996101893971236,
    "currentPrice": 363.739990234375,
    "name": "Marriott International"
  },
  {
    "symbol": "WAB",
    "momentum": 54.431534037695606,
    "currentPrice": 257.3800048828125,
    "name": "Wabtec"
  },
  {
    "symbol": "KEY",
    "momentum": 53.92967806480213,
    "currentPrice": 21.56999969482422,
    "name": "KeyCorp"
  },
  {
    "symbol": "TXT",
    "momentum": 52.943331979077634,
    "currentPrice": 90.48999786376953,
    "name": "Textron"
  },
  {
    "symbol": "AES",
    "momentum": 51.682326717037974,
    "currentPrice": 14.449999809265137,
    "name": "AES Corporation"
  },
  {
    "symbol": "NSC",
    "momentum": 51.52489463103878,
    "currentPrice": 297.7099914550781,
    "name": "Norfolk Southern"
  },
  {
    "symbol": "DVN",
    "momentum": 51.48291266863908,
    "currentPrice": 45.22999954223633,
    "name": "Devon Energy"
  },
  {
    "symbol": "RF",
    "momentum": 51.324167555211375,
    "currentPrice": 27.850000381469727,
    "name": "Regions Financial Corporation"
  },
  {
    "symbol": "RCL",
    "momentum": 51.22003147191665,
    "currentPrice": 282.30999755859375,
    "name": "Royal Caribbean Group"
  },
  {
    "symbol": "CVNA",
    "momentum": 51.1036813924064,
    "currentPrice": 371.0799865722656,
    "name": "Carvana"
  },
  {
    "symbol": "ADM",
    "momentum": 50.85812753200294,
    "currentPrice": 66.94999694824219,
    "name": "Archer Daniels Midland"
  },
  {
    "symbol": "SYF",
    "momentum": 50.8388388009224,
    "currentPrice": 75.98999786376953,
    "name": "Synchrony Financial"
  },
  {
    "symbol": "CASY",
    "momentum": 50.17071167906445,
    "currentPrice": 736.8300170898438,
    "name": "Casey's"
  },
  {
    "symbol": "UAL",
    "momentum": 49.99254599361108,
    "currentPrice": 94.2699966430664,
    "name": "United Airlines Holdings"
  },
  {
    "symbol": "EMR",
    "momentum": 49.6161681653203,
    "currentPrice": 140.39999389648438,
    "name": "Emerson Electric"
  },
  {
    "symbol": "AME",
    "momentum": 48.81818411701382,
    "currentPrice": 230.10000610351562,
    "name": "Ametek"
  },
  {
    "symbol": "XOM",
    "momentum": 48.73569559805477,
    "currentPrice": 149.00999450683594,
    "name": "ExxonMobil"
  },
  {
    "symbol": "USB",
    "momentum": 48.245737256350054,
    "currentPrice": 56.369998931884766,
    "name": "U.S. Bancorp"
  },
  {
    "symbol": "TDY",
    "momentum": 48.14163853214751,
    "currentPrice": 634.77001953125,
    "name": "Teledyne Technologies"
  },
  {
    "symbol": "FITB",
    "momentum": 47.8426588070583,
    "currentPrice": 49.84000015258789,
    "name": "Fifth Third Bancorp"
  },
  {
    "symbol": "PCAR",
    "momentum": 47.59145393615484,
    "currentPrice": 123.4800033569336,
    "name": "Paccar"
  },
  {
    "symbol": "TKO",
    "momentum": 47.5847161475249,
    "currentPrice": 193.10000610351562,
    "name": "TKO Group Holdings"
  },
  {
    "symbol": "CSCO",
    "momentum": 47.5709235617748,
    "currentPrice": 82.36000061035156,
    "name": "Cisco"
  },
  {
    "symbol": "HPE",
    "momentum": 47.53773353610426,
    "currentPrice": 24.6200008392334,
    "name": "Hewlett Packard Enterprise"
  },
  {
    "symbol": "ODFL",
    "momentum": 47.24457639337864,
    "currentPrice": 205.19000244140625,
    "name": "Old Dominion"
  },
  {
    "symbol": "URI",
    "momentum": 46.84727452162486,
    "currentPrice": 765.2899780273438,
    "name": "United Rentals"
  },
  {
    "symbol": "HUBB",
    "momentum": 46.663931326983864,
    "currentPrice": 526.9400024414062,
    "name": "Hubbell Incorporated"
  },
  {
    "symbol": "EXPE",
    "momentum": 46.19627378891687,
    "currentPrice": 257.44000244140625,
    "name": "Expedia Group"
  },
  {
    "symbol": "HLT",
    "momentum": 46.14703651667931,
    "currentPrice": 328.9100036621094,
    "name": "Hilton Worldwide"
  },
  {
    "symbol": "HSY",
    "momentum": 45.63571088537621,
    "currentPrice": 191.88999938964844,
    "name": "Hershey Company (The)"
  },
  {
    "symbol": "SWK",
    "momentum": 45.55358295277127,
    "currentPrice": 67.18000030517578,
    "name": "Stanley Black & Decker"
  },
  {
    "symbol": "BA",
    "momentum": 45.27385171932722,
    "currentPrice": 223.92999267578125,
    "name": "Boeing"
  },
  {
    "symbol": "NEE",
    "momentum": 45.26799062654883,
    "currentPrice": 91.23999786376953,
    "name": "NextEra Energy"
  },
  {
    "symbol": "WSM",
    "momentum": 44.87749295447969,
    "currentPrice": 192.8699951171875,
    "name": "Williams-Sonoma"
  },
  {
    "symbol": "PNC",
    "momentum": 44.75963723611782,
    "currentPrice": 222.05999755859375,
    "name": "PNC Financial Services"
  },
  {
    "symbol": "APTV",
    "momentum": 44.72490773938975,
    "currentPrice": 58.459999084472656,
    "name": "Aptiv"
  },
  {
    "symbol": "CF",
    "momentum": 44.59462762472895,
    "currentPrice": 120.80999755859375,
    "name": "CF Industries"
  },
  {
    "symbol": "SLB",
    "momentum": 44.52087429879769,
    "currentPrice": 52.41999816894531,
    "name": "Schlumberger"
  },
  {
    "symbol": "WELL",
    "momentum": 44.397510113380214,
    "currentPrice": 211.3300018310547,
    "name": "Welltower"
  },
  {
    "symbol": "GILD",
    "momentum": 44.261827914430675,
    "currentPrice": 139.77000427246094,
    "name": "Gilead Sciences"
  },
  {
    "symbol": "REGN",
    "momentum": 44.15282451786777,
    "currentPrice": 753.9299926757812,
    "name": "Regeneron Pharmaceuticals"
  },
  {
    "symbol": "TRGP",
    "momentum": 44.05808040795093,
    "currentPrice": 238.75,
    "name": "Targa Resources"
  },
  {
    "symbol": "CVX",
    "momentum": 43.618274848376146,
    "currentPrice": 184.91000366210938,
    "name": "Chevron Corporation"
  },
  {
    "symbol": "F",
    "momentum": 43.27745989919144,
    "currentPrice": 12.710000038146973,
    "name": "Ford Motor Company"
  },
  {
    "symbol": "PHM",
    "momentum": 43.17710547844032,
    "currentPrice": 120.81999969482422,
    "name": "PulteGroup"
  },
  {
    "symbol": "LMT",
    "momentum": 43.08578419147622,
    "currentPrice": 611.0999755859375,
    "name": "Lockheed Martin"
  },
  {
    "symbol": "TFC",
    "momentum": 42.983572633465414,
    "currentPrice": 49.59000015258789,
    "name": "Truist Financial"
  },
  {
    "symbol": "PLD",
    "momentum": 42.6983925445693,
    "currentPrice": 139.77000427246094,
    "name": "Prologis"
  },
  {
    "symbol": "NOC",
    "momentum": 42.500407278681536,
    "currentPrice": 678.5900268554688,
    "name": "Northrop Grumman"
  },
  {
    "symbol": "TXN",
    "momentum": 42.464010032756185,
    "currentPrice": 216.2899932861328,
    "name": "Texas Instruments"
  },
  {
    "symbol": "SPG",
    "momentum": 42.370317650657306,
    "currentPrice": 201.61000061035156,
    "name": "Simon Property Group"
  },
  {
    "symbol": "MTB",
    "momentum": 42.13838836041374,
    "currentPrice": 217.10000610351562,
    "name": "M&T Bank"
  },
  {
    "symbol": "OXY",
    "momentum": 41.77436989947157,
    "currentPrice": 55.83000183105469,
    "name": "Occidental Petroleum"
  },
  {
    "symbol": "EA",
    "momentum": 41.70458242114543,
    "currentPrice": 203.24000549316406,
    "name": "Electronic Arts"
  },
  {
    "symbol": "VST",
    "momentum": 41.51328769665365,
    "currentPrice": 162.94000244140625,
    "name": "Vistra Corp."
  },
  {
    "symbol": "MCK",
    "momentum": 41.439132523718676,
    "currentPrice": 863.4199829101562,
    "name": "McKesson Corporation"
  },
  {
    "symbol": "WYNN",
    "momentum": 41.427512874352416,
    "currentPrice": 106.83999633789062,
    "name": "Wynn Resorts"
  },
  {
    "symbol": "WMT",
    "momentum": 41.1119924161809,
    "currentPrice": 124.76000213623047,
    "name": "Walmart"
  },
  {
    "symbol": "EXPD",
    "momentum": 40.91681804351512,
    "currentPrice": 144.02000427246094,
    "name": "Expeditors International"
  },
  {
    "symbol": "EBAY",
    "momentum": 40.528957282572215,
    "currentPrice": 100.01000213623047,
    "name": "eBay Inc."
  },
  {
    "symbol": "BALL",
    "momentum": 39.64555100852633,
    "currentPrice": 62.7599983215332,
    "name": "Ball Corporation"
  },
  {
    "symbol": "AKAM",
    "momentum": 39.52039935400805,
    "currentPrice": 90.37999725341797,
    "name": "Akamai Technologies"
  },
  {
    "symbol": "TGT",
    "momentum": 38.825745932131255,
    "currentPrice": 122.87000274658203,
    "name": "Target Corporation"
  },
  {
    "symbol": "SRE",
    "momentum": 38.68283643395848,
    "currentPrice": 95.47000122070312,
    "name": "Sempra"
  },
  {
    "symbol": "CBOE",
    "momentum": 38.64298788404659,
    "currentPrice": 304.989990234375,
    "name": "Cboe Global Markets"
  },
  {
    "symbol": "FANG",
    "momentum": 38.57591286996086,
    "currentPrice": 185.8699951171875,
    "name": "Diamondback Energy"
  },
  {
    "symbol": "COP",
    "momentum": 38.5030338044402,
    "currentPrice": 118.91999816894531,
    "name": "ConocoPhillips"
  },
  {
    "symbol": "DOV",
    "momentum": 38.46309598345282,
    "currentPrice": 215.4600067138672,
    "name": "Dover Corporation"
  },
  {
    "symbol": "AMGN",
    "momentum": 38.39818535499789,
    "currentPrice": 348.2200012207031,
    "name": "Amgen"
  },
  {
    "symbol": "HON",
    "momentum": 37.91870526648565,
    "currentPrice": 232.19000244140625,
    "name": "Honeywell"
  },
  {
    "symbol": "LLY",
    "momentum": 37.569810912837376,
    "currentPrice": 905.030029296875,
    "name": "Lilly (Eli)"
  },
  {
    "symbol": "EIX",
    "momentum": 37.31029876744644,
    "currentPrice": 71.3499984741211,
    "name": "Edison International"
  },
  {
    "symbol": "DE",
    "momentum": 37.10122476973123,
    "currentPrice": 576.6400146484375,
    "name": "Deere & Company"
  },
  {
    "symbol": "BAC",
    "momentum": 37.00036559984444,
    "currentPrice": 54.31999969482422,
    "name": "Bank of America"
  },
  {
    "symbol": "AAPL",
    "momentum": 35.720467040010476,
    "currentPrice": 266.42999267578125,
    "name": "Apple Inc."
  },
  {
    "symbol": "MNST",
    "momentum": 35.6514229083923,
    "currentPrice": 74.93000030517578,
    "name": "Monster Beverage"
  },
  {
    "symbol": "MLM",
    "momentum": 35.244384742744685,
    "currentPrice": 616.9400024414062,
    "name": "Martin Marietta Materials"
  },
  {
    "symbol": "TT",
    "momentum": 35.20452786239242,
    "currentPrice": 462.55999755859375,
    "name": "Trane Technologies"
  },
  {
    "symbol": "GRMN",
    "momentum": 34.59934074699527,
    "currentPrice": 265.8399963378906,
    "name": "Garmin"
  },
  {
    "symbol": "PFG",
    "momentum": 34.35320805908991,
    "currentPrice": 94.68000030517578,
    "name": "Principal Financial Group"
  },
  {
    "symbol": "ES",
    "momentum": 34.32262248891645,
    "currentPrice": 68.7699966430664,
    "name": "Eversource Energy"
  },
  {
    "symbol": "GD",
    "momentum": 34.159497818899695,
    "currentPrice": 338.8800048828125,
    "name": "General Dynamics"
  },
  {
    "symbol": "WFC",
    "momentum": 34.02925139029084,
    "currentPrice": 80.29000091552734,
    "name": "Wells Fargo"
  },
  {
    "symbol": "IRM",
    "momentum": 33.991332922708764,
    "currentPrice": 113.55000305175781,
    "name": "Iron Mountain"
  },
  {
    "symbol": "CRH",
    "momentum": 33.73570688678497,
    "currentPrice": 116.20999908447266,
    "name": "CRH plc"
  },
  {
    "symbol": "WMB",
    "momentum": 33.35548620273852,
    "currentPrice": 70.76000213623047,
    "name": "Williams Companies"
  },
  {
    "symbol": "META",
    "momentum": 33.23249537145467,
    "currentPrice": 671.5800170898438,
    "name": "Meta Platforms"
  },
  {
    "symbol": "CTVA",
    "momentum": 33.04815745976749,
    "currentPrice": 81.31999969482422,
    "name": "Corteva"
  },
  {
    "symbol": "ETR",
    "momentum": 33.03760328558018,
    "currentPrice": 114.94999694824219,
    "name": "Entergy"
  },
  {
    "symbol": "ETN",
    "momentum": 32.90051021462254,
    "currentPrice": 395.05999755859375,
    "name": "Eaton Corporation"
  },
  {
    "symbol": "JPM",
    "momentum": 32.24969134163143,
    "currentPrice": 305.92999267578125,
    "name": "JPMorgan Chase"
  },
  {
    "symbol": "DHI",
    "momentum": 31.445459151623655,
    "currentPrice": 144.1999969482422,
    "name": "D. R. Horton"
  },
  {
    "symbol": "KMI",
    "momentum": 31.2941905367855,
    "currentPrice": 31.700000762939453,
    "name": "Kinder Morgan"
  },
  {
    "symbol": "BMY",
    "momentum": 31.23297986633819,
    "currentPrice": 57.88999938964844,
    "name": "Bristol Myers Squibb"
  },
  {
    "symbol": "NCLH",
    "momentum": 31.199505345910534,
    "currentPrice": 21.1200008392334,
    "name": "Norwegian Cruise Line Holdings"
  },
  {
    "symbol": "L",
    "momentum": 31.187582350114372,
    "currentPrice": 110.2300033569336,
    "name": "Loews Corporation"
  },
  {
    "symbol": "VTR",
    "momentum": 30.95824969784585,
    "currentPrice": 84.87000274658203,
    "name": "Ventas"
  },
  {
    "symbol": "HBAN",
    "momentum": 30.379868040912733,
    "currentPrice": 16.670000076293945,
    "name": "Huntington Bancshares"
  },
  {
    "symbol": "COR",
    "momentum": 30.372122214389112,
    "currentPrice": 317.5799865722656,
    "name": "Cencora"
  },
  {
    "symbol": "AEP",
    "momentum": 30.263418802400917,
    "currentPrice": 134.38999938964844,
    "name": "American Electric Power"
  },
  {
    "symbol": "NXPI",
    "momentum": 30.11216523827619,
    "currentPrice": 209.38999938964844,
    "name": "NXP Semiconductors"
  },
  {
    "symbol": "TJX",
    "momentum": 29.603937248000694,
    "currentPrice": 160.22999572753906,
    "name": "TJX Companies"
  },
  {
    "symbol": "FE",
    "momentum": 29.58108853285189,
    "currentPrice": 50.54999923706055,
    "name": "FirstEnergy"
  },
  {
    "symbol": "PFE",
    "momentum": 29.547437138632414,
    "currentPrice": 27.190000534057617,
    "name": "Pfizer"
  },
  {
    "symbol": "CINF",
    "momentum": 29.298450885961657,
    "currentPrice": 163.0,
    "name": "Cincinnati Financial"
  },
  {
    "symbol": "IEX",
    "momentum": 29.1803691474048,
    "currentPrice": 199.52000427246094,
    "name": "IDEX Corporation"
  },
  {
    "symbol": "MGM",
    "momentum": 28.882647523301692,
    "currentPrice": 38.36000061035156,
    "name": "MGM Resorts"
  },
  {
    "symbol": "IR",
    "momentum": 28.823654496057323,
    "currentPrice": 83.38999938964844,
    "name": "Ingersoll Rand"
  },
  {
    "symbol": "DDOG",
    "momentum": 28.787554819667534,
    "currentPrice": 121.05999755859375,
    "name": "Datadog"
  },
  {
    "symbol": "GEHC",
    "momentum": 28.764787441087496,
    "currentPrice": 73.51000213623047,
    "name": "GE HealthCare"
  },
  {
    "symbol": "LH",
    "momentum": 28.69614867787398,
    "currentPrice": 266.7300109863281,
    "name": "Labcorp"
  },
  {
    "symbol": "EVRG",
    "momentum": 28.683611578950334,
    "currentPrice": 81.54000091552734,
    "name": "Evergy"
  },
  {
    "symbol": "DGX",
    "momentum": 28.465624596822714,
    "currentPrice": 191.4199981689453,
    "name": "Quest Diagnostics"
  },
  {
    "symbol": "SCHW",
    "momentum": 28.43020896790539,
    "currentPrice": 100.2699966430664,
    "name": "Charles Schwab Corporation"
  },
  {
    "symbol": "EQIX",
    "momentum": 27.332236726025684,
    "currentPrice": 1052.97998046875,
    "name": "Equinix"
  },
  {
    "symbol": "ITW",
    "momentum": 27.321903590144114,
    "currentPrice": 264.3900146484375,
    "name": "Illinois Tool Works"
  },
  {
    "symbol": "HSIC",
    "momentum": 27.318692787829423,
    "currentPrice": 77.41999816894531,
    "name": "Henry Schein"
  },
  {
    "symbol": "ECL",
    "momentum": 27.21117286358043,
    "currentPrice": 270.3699951171875,
    "name": "Ecolab"
  },
  {
    "symbol": "LDOS",
    "momentum": 27.20855800120077,
    "currentPrice": 159.0399932861328,
    "name": "Leidos"
  },
  {
    "symbol": "PKG",
    "momentum": 26.84760197190956,
    "currentPrice": 207.07000732421875,
    "name": "Packaging Corporation of America"
  },
  {
    "symbol": "TPL",
    "momentum": 26.66548080962935,
    "currentPrice": 417.29998779296875,
    "name": "Texas Pacific Land Corporation"
  },
  {
    "symbol": "SYY",
    "momentum": 26.573893834197378,
    "currentPrice": 74.08999633789062,
    "name": "Sysco"
  },
  {
    "symbol": "MTD",
    "momentum": 26.558796368616918,
    "currentPrice": 1315.8499755859375,
    "name": "Mettler Toledo"
  },
  {
    "symbol": "LYV",
    "momentum": 26.446676667704715,
    "currentPrice": 155.82000732421875,
    "name": "Live Nation Entertainment"
  },
  {
    "symbol": "UNP",
    "momentum": 26.03421930209076,
    "currentPrice": 248.02999877929688,
    "name": "Union Pacific Corporation"
  },
  {
    "symbol": "DLR",
    "momentum": 25.978878123389133,
    "currentPrice": 195.69000244140625,
    "name": "Digital Realty"
  },
  {
    "symbol": "DIS",
    "momentum": 25.866298582789472,
    "currentPrice": 103.04000091552734,
    "name": "Walt Disney Company (The)"
  },
  {
    "symbol": "DOW",
    "momentum": 25.695673298537375,
    "currentPrice": 38.84000015258789,
    "name": "Dow Inc."
  },
  {
    "symbol": "ALLE",
    "momentum": 25.643906950869948,
    "currentPrice": 141.63999938964844,
    "name": "Allegion"
  },
  {
    "symbol": "MMM",
    "momentum": 25.59781158577841,
    "currentPrice": 151.24000549316406,
    "name": "3M"
  },
  {
    "symbol": "NI",
    "momentum": 25.471366671748896,
    "currentPrice": 47.369998931884766,
    "name": "NiSource"
  },
  {
    "symbol": "NDAQ",
    "momentum": 25.441749933162033,
    "currentPrice": 88.55000305175781,
    "name": "Nasdaq"
  },
  {
    "symbol": "UPS",
    "momentum": 25.3208503863426,
    "currentPrice": 103.56999969482422,
    "name": "United Parcel Service"
  },
  {
    "symbol": "MO",
    "momentum": 25.215052333708606,
    "currentPrice": 64.41999816894531,
    "name": "Altria"
  },
  {
    "symbol": "TRV",
    "momentum": 25.089717695766424,
    "currentPrice": 299.3299865722656,
    "name": "Travelers Companies (The)"
  },
  {
    "symbol": "AMZN",
    "momentum": 24.37331787235432,
    "currentPrice": 248.5,
    "name": "Amazon"
  },
  {
    "symbol": "CME",
    "momentum": 24.1408762666902,
    "currentPrice": 296.8999938964844,
    "name": "CME Group"
  },
  {
    "symbol": "NTAP",
    "momentum": 24.104154872123733,
    "currentPrice": 100.33000183105469,
    "name": "NetApp"
  },
  {
    "symbol": "COF",
    "momentum": 24.013221593788206,
    "currentPrice": 202.97999572753906,
    "name": "Capital One"
  },
  {
    "symbol": "AXP",
    "momentum": 23.94476445556516,
    "currentPrice": 329.05999755859375,
    "name": "American Express"
  },
  {
    "symbol": "OMC",
    "momentum": 23.938817302514398,
    "currentPrice": 77.48999786376953,
    "name": "Omnicom Group"
  },
  {
    "symbol": "FRT",
    "momentum": 23.848097939646223,
    "currentPrice": 110.1500015258789,
    "name": "Federal Realty Investment Trust"
  },
  {
    "symbol": "AIZ",
    "momentum": 23.786812164516675,
    "currentPrice": 224.00999450683594,
    "name": "Assurant"
  },
  {
    "symbol": "VMC",
    "momentum": 23.680934862827165,
    "currentPrice": 291.25,
    "name": "Vulcan Materials Company"
  },
  {
    "symbol": "SBUX",
    "momentum": 23.61387981627285,
    "currentPrice": 98.33999633789062,
    "name": "Starbucks"
  },
  {
    "symbol": "RMD",
    "momentum": 23.588157212935673,
    "currentPrice": 228.8000030517578,
    "name": "ResMed"
  },
  {
    "symbol": "LNT",
    "momentum": 23.514442115602353,
    "currentPrice": 72.18000030517578,
    "name": "Alliant Energy"
  },
  {
    "symbol": "VZ",
    "momentum": 23.458838560482164,
    "currentPrice": 45.029998779296875,
    "name": "Verizon"
  },
  {
    "symbol": "HIG",
    "momentum": 23.38964954887588,
    "currentPrice": 138.75,
    "name": "Hartford (The)"
  },
  {
    "symbol": "D",
    "momentum": 23.385415330652997,
    "currentPrice": 62.380001068115234,
    "name": "Dominion Energy"
  },
  {
    "symbol": "XEL",
    "momentum": 23.065269011807562,
    "currentPrice": 78.6500015258789,
    "name": "Xcel Energy"
  },
  {
    "symbol": "LOW",
    "momentum": 23.050290918135634,
    "currentPrice": 243.99000549316406,
    "name": "Lowe's"
  },
  {
    "symbol": "BLK",
    "momentum": 23.001778320377987,
    "currentPrice": 1048.5999755859375,
    "name": "BlackRock"
  },
  {
    "symbol": "PPG",
    "momentum": 22.74308079191507,
    "currentPrice": 107.72000122070312,
    "name": "PPG Industries"
  },
  {
    "symbol": "CNP",
    "momentum": 22.449025285054542,
    "currentPrice": 42.47999954223633,
    "name": "CenterPoint Energy"
  },
  {
    "symbol": "CTRA",
    "momentum": 22.388133223381654,
    "currentPrice": 31.600000381469727,
    "name": "Coterra"
  },
  {
    "symbol": "FOXA",
    "momentum": 22.20693106867501,
    "currentPrice": 63.65999984741211,
    "name": "Fox Corporation (Class A)"
  },
  {
    "symbol": "ATO",
    "momentum": 22.14464652157721,
    "currentPrice": 186.25999450683594,
    "name": "Atmos Energy"
  },
  {
    "symbol": "CVS",
    "momentum": 22.018462788455075,
    "currentPrice": 74.98999786376953,
    "name": "CVS Health"
  },
  {
    "symbol": "EQT",
    "momentum": 22.000895115834457,
    "currentPrice": 56.7599983215332,
    "name": "EQT Corporation"
  },
  {
    "symbol": "XYZ",
    "momentum": 21.376740211664245,
    "currentPrice": 67.97000122070312,
    "name": "Block"
  },
  {
    "symbol": "EOG",
    "momentum": 21.355806803930122,
    "currentPrice": 132.38999938964844,
    "name": "EOG Resources"
  },
  {
    "symbol": "COIN",
    "momentum": 21.32279457077403,
    "currentPrice": 195.89999389648438,
    "name": "Coinbase"
  },
  {
    "symbol": "PNR",
    "momentum": 21.31389748215212,
    "currentPrice": 88.3499984741211,
    "name": "Pentair"
  },
  {
    "symbol": "O",
    "momentum": 21.2480857041413,
    "currentPrice": 63.959999084472656,
    "name": "Realty Income"
  },
  {
    "symbol": "KIM",
    "momentum": 21.144377926680775,
    "currentPrice": 23.479999542236328,
    "name": "Kimco Realty"
  },
  {
    "symbol": "LYB",
    "momentum": 20.94110795826239,
    "currentPrice": 73.12999725341797,
    "name": "LyondellBasell"
  },
  {
    "symbol": "CBRE",
    "momentum": 20.92825407413642,
    "currentPrice": 147.47999572753906,
    "name": "CBRE Group"
  },
  {
    "symbol": "J",
    "momentum": 20.85400866433385,
    "currentPrice": 127.30999755859375,
    "name": "Jacobs Solutions"
  },
  {
    "symbol": "PEP",
    "momentum": 20.619944259551744,
    "currentPrice": 154.85000610351562,
    "name": "PepsiCo"
  },
  {
    "symbol": "FOX",
    "momentum": 20.351113803488545,
    "currentPrice": 57.04999923706055,
    "name": "Fox Corporation (Class B)"
  },
  {
    "symbol": "ABNB",
    "momentum": 20.330250373375687,
    "currentPrice": 137.50999450683594,
    "name": "Airbnb"
  },
  {
    "symbol": "GL",
    "momentum": 20.146160221979915,
    "currentPrice": 149.0800018310547,
    "name": "Globe Life"
  },
  {
    "symbol": "TRMB",
    "momentum": 19.972545699131654,
    "currentPrice": 66.79000091552734,
    "name": "Trimble Inc."
  },
  {
    "symbol": "XYL",
    "momentum": 19.959727485071973,
    "currentPrice": 125.19000244140625,
    "name": "Xylem Inc."
  },
  {
    "symbol": "IQV",
    "momentum": 19.832930448129783,
    "currentPrice": 178.10000610351562,
    "name": "IQVIA"
  },
  {
    "symbol": "EW",
    "momentum": 19.69101808059427,
    "currentPrice": 78.19999694824219,
    "name": "Edwards Lifesciences"
  },
  {
    "symbol": "WST",
    "momentum": 19.40814833575584,
    "currentPrice": 266.5,
    "name": "West Pharmaceutical Services"
  },
  {
    "symbol": "RJF",
    "momentum": 19.243210235431537,
    "currentPrice": 155.77000427246094,
    "name": "Raymond James Financial"
  },
  {
    "symbol": "AOS",
    "momentum": 19.073931035285668,
    "currentPrice": 63.369998931884766,
    "name": "A. O. Smith"
  },
  {
    "symbol": "FTV",
    "momentum": 18.82024467325734,
    "currentPrice": 59.369998931884766,
    "name": "Fortive"
  },
  {
    "symbol": "SNA",
    "momentum": 18.656411869825995,
    "currentPrice": 368.010009765625,
    "name": "Snap-on"
  },
  {
    "symbol": "MDT",
    "momentum": 18.30661210863835,
    "currentPrice": 87.0999984741211,
    "name": "Medtronic"
  },
  {
    "symbol": "ORCL",
    "momentum": 18.18979535432062,
    "currentPrice": 169.80999755859375,
    "name": "Oracle Corporation"
  },
  {
    "symbol": "AEE",
    "momentum": 18.183163887850462,
    "currentPrice": 110.73999786376953,
    "name": "Ameren"
  },
  {
    "symbol": "A",
    "momentum": 18.065002579110768,
    "currentPrice": 119.7699966430664,
    "name": "Agilent Technologies"
  },
  {
    "symbol": "FAST",
    "momentum": 17.850303481805714,
    "currentPrice": 44.400001525878906,
    "name": "Fastenal"
  },
  {
    "symbol": "CDNS",
    "momentum": 17.80837042777813,
    "currentPrice": 304.1000061035156,
    "name": "Cadence Design Systems"
  },
  {
    "symbol": "TMO",
    "momentum": 17.692333962190453,
    "currentPrice": 531.6699829101562,
    "name": "Thermo Fisher Scientific"
  },
  {
    "symbol": "CB",
    "momentum": 17.60766823414077,
    "currentPrice": 327.2699890136719,
    "name": "Chubb Limited"
  },
  {
    "symbol": "BBY",
    "momentum": 17.594532121985722,
    "currentPrice": 63.38999938964844,
    "name": "Best Buy"
  },
  {
    "symbol": "GWW",
    "momentum": 17.588571534273374,
    "currentPrice": 1143.3499755859375,
    "name": "W. W. Grainger"
  },
  {
    "symbol": "UHS",
    "momentum": 16.95829816198015,
    "currentPrice": 180.14999389648438,
    "name": "Universal Health Services"
  },
  {
    "symbol": "REG",
    "momentum": 16.918201325115696,
    "currentPrice": 79.5199966430664,
    "name": "Regency Centers"
  },
  {
    "symbol": "DTE",
    "momentum": 16.593319422381345,
    "currentPrice": 146.75,
    "name": "DTE Energy"
  },
  {
    "symbol": "TECH",
    "momentum": 16.421368518388437,
    "currentPrice": 58.4900016784668,
    "name": "Bio-Techne"
  },
  {
    "symbol": "PNW",
    "momentum": 14.705828869989402,
    "currentPrice": 102.80000305175781,
    "name": "Pinnacle West Capital"
  },
  {
    "symbol": "MSI",
    "momentum": 14.677683592666266,
    "currentPrice": 440.2099914550781,
    "name": "Motorola Solutions"
  },
  {
    "symbol": "MAS",
    "momentum": 14.541509283148347,
    "currentPrice": 63.16999816894531,
    "name": "Masco"
  },
  {
    "symbol": "PM",
    "momentum": 14.496350804760475,
    "currentPrice": 157.19000244140625,
    "name": "Philip Morris International"
  },
  {
    "symbol": "SW",
    "momentum": 13.988513092147848,
    "currentPrice": 41.400001525878906,
    "name": "Smurfit Westrock"
  },
  {
    "symbol": "PSKY",
    "momentum": 13.722326628181866,
    "currentPrice": 11.670000076293945,
    "name": "Paramount Skydance Corporation"
  },
  {
    "symbol": "AVY",
    "momentum": 13.717904522794258,
    "currentPrice": 168.02999877929688,
    "name": "Avery Dennison"
  },
  {
    "symbol": "YUM",
    "momentum": 13.662887892012735,
    "currentPrice": 161.94000244140625,
    "name": "Yum! Brands"
  },
  {
    "symbol": "DUK",
    "momentum": 13.460616624368358,
    "currentPrice": 127.9800033569336,
    "name": "Duke Energy"
  },
  {
    "symbol": "WEC",
    "momentum": 13.191260401079083,
    "currentPrice": 114.8499984741211,
    "name": "WEC Energy Group"
  },
  {
    "symbol": "PTC",
    "momentum": 13.189336058253435,
    "currentPrice": 136.5800018310547,
    "name": "PTC Inc."
  },
  {
    "symbol": "EXR",
    "momentum": 12.554056681941441,
    "currentPrice": 141.05999755859375,
    "name": "Extra Space Storage"
  },
  {
    "symbol": "LIN",
    "momentum": 12.553756236206679,
    "currentPrice": 497.94000244140625,
    "name": "Linde plc"
  },
  {
    "symbol": "ALL",
    "momentum": 12.43593598781416,
    "currentPrice": 218.22999572753906,
    "name": "Allstate"
  },
  {
    "symbol": "NKE",
    "momentum": 12.253315980896351,
    "currentPrice": 45.439998626708984,
    "name": "Nike"
  },
  {
    "symbol": "IFF",
    "momentum": 12.0434055406354,
    "currentPrice": 71.52999877929688,
    "name": "International Flavors & Fragrances"
  },
  {
    "symbol": "PPL",
    "momentum": 12.023409501831823,
    "currentPrice": 39.36000061035156,
    "name": "PPL Corporation"
  },
  {
    "symbol": "TROW",
    "momentum": 11.90503371926148,
    "currentPrice": 96.11000061035156,
    "name": "T. Rowe Price"
  },
  {
    "symbol": "MCO",
    "momentum": 11.521291139313677,
    "currentPrice": 446.80999755859375,
    "name": "Moody's Corporation"
  },
  {
    "symbol": "CMS",
    "momentum": 11.519625060977583,
    "currentPrice": 77.4800033569336,
    "name": "CMS Energy"
  },
  {
    "symbol": "SO",
    "momentum": 11.4558277154217,
    "currentPrice": 94.63999938964844,
    "name": "Southern Company"
  },
  {
    "symbol": "KO",
    "momentum": 11.349339218917398,
    "currentPrice": 75.30999755859375,
    "name": "Coca-Cola Company (The)"
  },
  {
    "symbol": "STE",
    "momentum": 11.307233416606161,
    "currentPrice": 221.5,
    "name": "Steris"
  },
  {
    "symbol": "PSA",
    "momentum": 10.940214247540696,
    "currentPrice": 299.8299865722656,
    "name": "Public Storage"
  },
  {
    "symbol": "SYK",
    "momentum": 10.92207059814801,
    "currentPrice": 341.239990234375,
    "name": "Stryker Corporation"
  },
  {
    "symbol": "T",
    "momentum": 10.775487711845832,
    "currentPrice": 25.459999084472656,
    "name": "AT&T"
  },
  {
    "symbol": "BDX",
    "momentum": 10.701007480418694,
    "currentPrice": 155.52000427246094,
    "name": "Becton Dickinson"
  },
  {
    "symbol": "PCG",
    "momentum": 10.618981458496096,
    "currentPrice": 17.389999389648438,
    "name": "PG&E Corporation"
  },
  {
    "symbol": "FFIV",
    "momentum": 10.479567140141995,
    "currentPrice": 299.0899963378906,
    "name": "F5"
  },
  {
    "symbol": "MSFT",
    "momentum": 9.873810067406723,
    "currentPrice": 411.2200012207031,
    "name": "Microsoft"
  },
  {
    "symbol": "MCD",
    "momentum": 9.807310900448847,
    "currentPrice": 306.260009765625,
    "name": "McDonald's"
  },
  {
    "symbol": "EXC",
    "momentum": 9.659990624543193,
    "currentPrice": 47.880001068115234,
    "name": "Exelon"
  },
  {
    "symbol": "DVA",
    "momentum": 9.39222140362743,
    "currentPrice": 144.57000732421875,
    "name": "DaVita"
  },
  {
    "symbol": "ALGN",
    "momentum": 8.960408926072542,
    "currentPrice": 186.52999877929688,
    "name": "Align Technology"
  },
  {
    "symbol": "HD",
    "momentum": 8.652483308522992,
    "currentPrice": 338.9100036621094,
    "name": "Home Depot (The)"
  },
  {
    "symbol": "DHR",
    "momentum": 7.889607527347022,
    "currentPrice": 198.13999938964844,
    "name": "Danaher Corporation"
  },
  {
    "symbol": "WM",
    "momentum": 7.446839448173543,
    "currentPrice": 224.92999267578125,
    "name": "Waste Management"
  },
  {
    "symbol": "IBM",
    "momentum": 7.42177557500025,
    "currentPrice": 244.8000030517578,
    "name": "IBM"
  },
  {
    "symbol": "TSN",
    "momentum": 7.395979088708906,
    "currentPrice": 63.380001068115234,
    "name": "Tyson Foods"
  },
  {
    "symbol": "CRWD",
    "momentum": 7.329400959957168,
    "currentPrice": 411.1600036621094,
    "name": "CrowdStrike"
  },
  {
    "symbol": "SOLV",
    "momentum": 7.202685379653878,
    "currentPrice": 69.0999984741211,
    "name": "Solventum"
  },
  {
    "symbol": "CPAY",
    "momentum": 7.155201940582591,
    "currentPrice": 323.9599914550781,
    "name": "Corpay"
  },
  {
    "symbol": "APD",
    "momentum": 7.072529301040423,
    "currentPrice": 295.2099914550781,
    "name": "Air Products"
  },
  {
    "symbol": "AFL",
    "momentum": 7.060490752104105,
    "currentPrice": 112.9800033569336,
    "name": "Aflac"
  },
  {
    "symbol": "MSCI",
    "momentum": 6.917215036231326,
    "currentPrice": 560.0599975585938,
    "name": "MSCI Inc."
  },
  {
    "symbol": "ROL",
    "momentum": 6.696181236713724,
    "currentPrice": 54.380001068115234,
    "name": "Rollins"
  },
  {
    "symbol": "ACGL",
    "momentum": 6.53821291957645,
    "currentPrice": 97.47000122070312,
    "name": "Arch Capital Group"
  },
  {
    "symbol": "VLTO",
    "momentum": 6.374565457731589,
    "currentPrice": 92.31999969482422,
    "name": "Veralto"
  },
  {
    "symbol": "DXCM",
    "momentum": 6.067216594315263,
    "currentPrice": 61.540000915527344,
    "name": "Dexcom"
  },
  {
    "symbol": "SHW",
    "momentum": 5.885099139736216,
    "currentPrice": 328.8399963378906,
    "name": "Sherwin-Williams"
  },
  {
    "symbol": "ICE",
    "momentum": 5.845523199192436,
    "currentPrice": 165.07000732421875,
    "name": "Intercontinental Exchange"
  },
  {
    "symbol": "WRB",
    "momentum": 5.582308617318864,
    "currentPrice": 66.0999984741211,
    "name": "W. R. Berkley Corporation"
  },
  {
    "symbol": "DECK",
    "momentum": 5.552321303718563,
    "currentPrice": 108.87000274658203,
    "name": "Deckers Brands"
  },
  {
    "symbol": "GPC",
    "momentum": 5.539723769193284,
    "currentPrice": 110.44000244140625,
    "name": "Genuine Parts Company"
  },
  {
    "symbol": "OKE",
    "momentum": 5.524062543188054,
    "currentPrice": 84.0999984741211,
    "name": "Oneok"
  },
  {
    "symbol": "LEN",
    "momentum": 5.519181183668411,
    "currentPrice": 88.44000244140625,
    "name": "Lennar"
  },
  {
    "symbol": "PRU",
    "momentum": 5.511255965492222,
    "currentPrice": 99.41999816894531,
    "name": "Prudential Financial"
  },
  {
    "symbol": "RVTY",
    "momentum": 5.35390887627963,
    "currentPrice": 92.9000015258789,
    "name": "Revvity"
  },
  {
    "symbol": "CMCSA",
    "momentum": 5.30562882069664,
    "currentPrice": 28.299999237060547,
    "name": "Comcast"
  },
  {
    "symbol": "MET",
    "momentum": 5.302189659451443,
    "currentPrice": 77.5199966430664,
    "name": "MetLife"
  },
  {
    "symbol": "TDG",
    "momentum": 5.182143372145142,
    "currentPrice": 1274.68994140625,
    "name": "TransDigm Group"
  },
  {
    "symbol": "SWKS",
    "momentum": 5.145556056255558,
    "currentPrice": 57.93000030517578,
    "name": "Skyworks Solutions"
  },
  {
    "symbol": "DRI",
    "momentum": 5.136543716536432,
    "currentPrice": 199.67999267578125,
    "name": "Darden Restaurants"
  },
  {
    "symbol": "UBER",
    "momentum": 4.9137750988918265,
    "currentPrice": 77.27999877929688,
    "name": "Uber"
  },
  {
    "symbol": "COO",
    "momentum": 4.793557253078699,
    "currentPrice": 70.29000091552734,
    "name": "Cooper Companies (The)"
  },
  {
    "symbol": "CARR",
    "momentum": 4.678053204353083,
    "currentPrice": 58.54999923706055,
    "name": "Carrier Global"
  },
  {
    "symbol": "COST",
    "momentum": 4.599055601700379,
    "currentPrice": 984.75,
    "name": "Costco"
  },
  {
    "symbol": "QCOM",
    "momentum": 4.514464357330267,
    "currentPrice": 133.0500030517578,
    "name": "Qualcomm"
  },
  {
    "symbol": "CL",
    "momentum": 4.425997504018865,
    "currentPrice": 83.48999786376953,
    "name": "Colgate-Palmolive"
  },
  {
    "symbol": "ED",
    "momentum": 4.311923042175249,
    "currentPrice": 110.27999877929688,
    "name": "Consolidated Edison"
  },
  {
    "symbol": "TSCO",
    "momentum": 4.263231883332171,
    "currentPrice": 44.75,
    "name": "Tractor Supply"
  },
  {
    "symbol": "AZO",
    "momentum": 4.2093014039355205,
    "currentPrice": 3536.419921875,
    "name": "AutoZone"
  },
  {
    "symbol": "ISRG",
    "momentum": 4.121825838043046,
    "currentPrice": 468.3599853515625,
    "name": "Intuitive Surgical"
  },
  {
    "symbol": "SJM",
    "momentum": 3.933013242950536,
    "currentPrice": 93.48999786376953,
    "name": "J.M. Smucker Company (The)"
  },
  {
    "symbol": "SNPS",
    "momentum": 3.688203371816148,
    "currentPrice": 438.45001220703125,
    "name": "Synopsys"
  },
  {
    "symbol": "EXE",
    "momentum": 3.660028737091065,
    "currentPrice": 96.05000305175781,
    "name": "Expand Energy"
  },
  {
    "symbol": "ORLY",
    "momentum": 3.641993430610403,
    "currentPrice": 93.5999984741211,
    "name": "O\u2019Reilly Automotive"
  },
  {
    "symbol": "PEG",
    "momentum": 3.488440915545126,
    "currentPrice": 80.94000244140625,
    "name": "Public Service Enterprise Group"
  },
  {
    "symbol": "ZBRA",
    "momentum": 2.963162406513947,
    "currentPrice": 229.63999938964844,
    "name": "Zebra Technologies"
  },
  {
    "symbol": "NVR",
    "momentum": 2.9277497231113,
    "currentPrice": 6767.2099609375,
    "name": "NVR"
  },
  {
    "symbol": "NFLX",
    "momentum": 2.596634459874216,
    "currentPrice": 107.70999908447266,
    "name": "Netflix"
  },
  {
    "symbol": "AMP",
    "momentum": 2.5455247544919435,
    "currentPrice": 468.1499938964844,
    "name": "Ameriprise Financial"
  },
  {
    "symbol": "SMCI",
    "momentum": 2.383198967627347,
    "currentPrice": 27.290000915527344,
    "name": "Supermicro"
  },
  {
    "symbol": "MA",
    "momentum": 2.274191985175017,
    "currentPrice": 519.9600219726562,
    "name": "Mastercard"
  },
  {
    "symbol": "TTWO",
    "momentum": 2.06717620725969,
    "currentPrice": 214.14999389648438,
    "name": "Take-Two Interactive"
  },
  {
    "symbol": "AMCR",
    "momentum": 1.9229846825279124,
    "currentPrice": 40.599998474121094,
    "name": "Amcor"
  },
  {
    "symbol": "CPT",
    "momentum": 1.606994020316425,
    "currentPrice": 101.37999725341797,
    "name": "Camden Property Trust"
  },
  {
    "symbol": "LII",
    "momentum": 1.480520262859158,
    "currentPrice": 484.2900085449219,
    "name": "Lennox International"
  },
  {
    "symbol": "DOC",
    "momentum": 1.2613818875410456,
    "currentPrice": 17.200000762939453,
    "name": "Healthpeak Properties"
  },
  {
    "symbol": "CHD",
    "momentum": 0.818917608533888,
    "currentPrice": 94.62999725341797,
    "name": "Church & Dwight"
  },
  {
    "symbol": "KR",
    "momentum": 0.5349289408774743,
    "currentPrice": 66.62999725341797,
    "name": "Kroger"
  },
  {
    "symbol": "AXON",
    "momentum": -0.35673307938039467,
    "currentPrice": 402.17999267578125,
    "name": "Axon Enterprise"
  },
  {
    "symbol": "ZBH",
    "momentum": -0.4651423189169699,
    "currentPrice": 94.19999694824219,
    "name": "Zimmer Biomet"
  },
  {
    "symbol": "WY",
    "momentum": -0.483870880650711,
    "currentPrice": 24.209999084472656,
    "name": "Weyerhaeuser"
  },
  {
    "symbol": "WAT",
    "momentum": -0.6415439176072927,
    "currentPrice": 326.20001220703125,
    "name": "Waters Corporation"
  },
  {
    "symbol": "ADSK",
    "momentum": -0.8725357402055126,
    "currentPrice": 239.32000732421875,
    "name": "Autodesk"
  },
  {
    "symbol": "DASH",
    "momentum": -0.9142089276037271,
    "currentPrice": 179.93499755859375,
    "name": "DoorDash"
  },
  {
    "symbol": "JKHY",
    "momentum": -1.0110182356800244,
    "currentPrice": 153.39999389648438,
    "name": "Jack Henry & Associates"
  },
  {
    "symbol": "CTAS",
    "momentum": -1.4073681827079818,
    "currentPrice": 176.4600067138672,
    "name": "Cintas"
  },
  {
    "symbol": "MOS",
    "momentum": -1.4217651205880386,
    "currentPrice": 23.729999542236328,
    "name": "Mosaic Company (The)"
  },
  {
    "symbol": "VRTX",
    "momentum": -1.6464631416203,
    "currentPrice": 441.70001220703125,
    "name": "Vertex Pharmaceuticals"
  },
  {
    "symbol": "VRSN",
    "momentum": -1.675324016129004,
    "currentPrice": 275.260009765625,
    "name": "Verisign"
  },
  {
    "symbol": "AIG",
    "momentum": -1.7038692490498921,
    "currentPrice": 77.08999633789062,
    "name": "American International Group"
  },
  {
    "symbol": "PG",
    "momentum": -2.2512363992315665,
    "currentPrice": 143.3800048828125,
    "name": "Procter & Gamble"
  },
  {
    "symbol": "V",
    "momentum": -2.553819143180867,
    "currentPrice": 315.9100036621094,
    "name": "Visa Inc."
  },
  {
    "symbol": "VICI",
    "momentum": -2.6017998443019406,
    "currentPrice": 28.1299991607666,
    "name": "Vici Properties"
  },
  {
    "symbol": "ESS",
    "momentum": -3.0880954432288417,
    "currentPrice": 251.7100067138672,
    "name": "Essex Property Trust"
  },
  {
    "symbol": "PODD",
    "momentum": -3.1268681336436983,
    "currentPrice": 202.5,
    "name": "Insulet Corporation"
  },
  {
    "symbol": "SPGI",
    "momentum": -3.222625608308214,
    "currentPrice": 430.5799865722656,
    "name": "S&P Global"
  },
  {
    "symbol": "EG",
    "momentum": -3.318413997831277,
    "currentPrice": 345.6099853515625,
    "name": "Everest Group"
  },
  {
    "symbol": "EQR",
    "momentum": -3.3399879778884456,
    "currentPrice": 61.29999923706055,
    "name": "Equity Residential"
  },
  {
    "symbol": "OTIS",
    "momentum": -4.073530378810062,
    "currentPrice": 81.0,
    "name": "Otis Worldwide"
  },
  {
    "symbol": "IP",
    "momentum": -4.134761950076283,
    "currentPrice": 36.5099983215332,
    "name": "International Paper"
  },
  {
    "symbol": "RSG",
    "momentum": -4.171111460939234,
    "currentPrice": 210.8699951171875,
    "name": "Republic Services"
  },
  {
    "symbol": "EPAM",
    "momentum": -4.331888196423136,
    "currentPrice": 128.4199981689453,
    "name": "EPAM Systems"
  },
  {
    "symbol": "UDR",
    "momentum": -4.411206023292094,
    "currentPrice": 34.86000061035156,
    "name": "UDR"
  },
  {
    "symbol": "AWK",
    "momentum": -4.478984399107935,
    "currentPrice": 130.30999755859375,
    "name": "American Water Works"
  },
  {
    "symbol": "EFX",
    "momentum": -5.203325681986119,
    "currentPrice": 186.85000610351562,
    "name": "Equifax"
  },
  {
    "symbol": "CTSH",
    "momentum": -5.324343699534387,
    "currentPrice": 60.38999938964844,
    "name": "Cognizant"
  },
  {
    "symbol": "WTW",
    "momentum": -5.434359131531834,
    "currentPrice": 292.1499938964844,
    "name": "Willis Towers Watson"
  },
  {
    "symbol": "BKNG",
    "momentum": -5.823041425033196,
    "currentPrice": 185.69000244140625,
    "name": "Booking Holdings"
  },
  {
    "symbol": "NWSA",
    "momentum": -6.069502602023971,
    "currentPrice": 25.329999923706055,
    "name": "News Corp (Class A)"
  },
  {
    "symbol": "GEN",
    "momentum": -6.5735214337484225,
    "currentPrice": 19.670000076293945,
    "name": "Gen Digital"
  },
  {
    "symbol": "PANW",
    "momentum": -6.5975478974177175,
    "currentPrice": 164.11000061035156,
    "name": "Palo Alto Networks"
  },
  {
    "symbol": "CCI",
    "momentum": -6.894884119342668,
    "currentPrice": 85.62999725341797,
    "name": "Crown Castle"
  },
  {
    "symbol": "GPN",
    "momentum": -6.939483576732155,
    "currentPrice": 70.16999816894531,
    "name": "Global Payments"
  },
  {
    "symbol": "KKR",
    "momentum": -7.480303291323217,
    "currentPrice": 103.8499984741211,
    "name": "KKR & Co."
  },
  {
    "symbol": "BXP",
    "momentum": -7.559874670898849,
    "currentPrice": 55.93000030517578,
    "name": "BXP"
  },
  {
    "symbol": "AON",
    "momentum": -8.10163693188072,
    "currentPrice": 328.0799865722656,
    "name": "Aon plc"
  },
  {
    "symbol": "AVB",
    "momentum": -8.523315990320878,
    "currentPrice": 171.2899932861328,
    "name": "AvalonBay Communities"
  },
  {
    "symbol": "BX",
    "momentum": -8.775733689224785,
    "currentPrice": 130.19000244140625,
    "name": "Blackstone Inc."
  },
  {
    "symbol": "MKC",
    "momentum": -8.864961359233822,
    "currentPrice": 53.34000015258789,
    "name": "McCormick & Company"
  },
  {
    "symbol": "MDLZ",
    "momentum": -9.560922640315091,
    "currentPrice": 56.58000183105469,
    "name": "Mondelez International"
  },
  {
    "symbol": "NWS",
    "momentum": -10.008387351301053,
    "currentPrice": 29.149999618530273,
    "name": "News Corp (Class B)"
  },
  {
    "symbol": "AMT",
    "momentum": -10.14472568615295,
    "currentPrice": 176.99000549316406,
    "name": "American Tower"
  },
  {
    "symbol": "CLX",
    "momentum": -10.639478905699182,
    "currentPrice": 102.91999816894531,
    "name": "Clorox"
  },
  {
    "symbol": "APO",
    "momentum": -10.972061275524378,
    "currentPrice": 120.54000091552734,
    "name": "Apollo Global Management"
  },
  {
    "symbol": "DPZ",
    "momentum": -10.993983557756819,
    "currentPrice": 368.07000732421875,
    "name": "Domino's"
  },
  {
    "symbol": "SBAC",
    "momentum": -11.615639022694149,
    "currentPrice": 214.1999969482422,
    "name": "SBA Communications"
  },
  {
    "symbol": "CI",
    "momentum": -12.223190767925361,
    "currentPrice": 268.6300048828125,
    "name": "Cigna"
  },
  {
    "symbol": "KHC",
    "momentum": -12.695053363453384,
    "currentPrice": 22.010000228881836,
    "name": "Kraft Heinz"
  },
  {
    "symbol": "ZTS",
    "momentum": -12.924119572508378,
    "currentPrice": 120.76000213623047,
    "name": "Zoetis"
  },
  {
    "symbol": "FTNT",
    "momentum": -13.823252650652748,
    "currentPrice": 79.63999938964844,
    "name": "Fortinet"
  },
  {
    "symbol": "TMUS",
    "momentum": -13.933171483624193,
    "currentPrice": 190.19000244140625,
    "name": "T-Mobile US"
  },
  {
    "symbol": "CDW",
    "momentum": -14.65637729615408,
    "currentPrice": 129.55999755859375,
    "name": "CDW Corporation"
  },
  {
    "symbol": "BLDR",
    "momentum": -15.098178014710845,
    "currentPrice": 85.12999725341797,
    "name": "Builders FirstSource"
  },
  {
    "symbol": "ARES",
    "momentum": -15.118902978039339,
    "currentPrice": 119.27999877929688,
    "name": "Ares Management"
  },
  {
    "symbol": "STZ",
    "momentum": -15.223556673325616,
    "currentPrice": 163.9499969482422,
    "name": "Constellation Brands"
  },
  {
    "symbol": "HPQ",
    "momentum": -15.518959477109004,
    "currentPrice": 19.229999542236328,
    "name": "HP Inc."
  },
  {
    "symbol": "KDP",
    "momentum": -15.758282329977552,
    "currentPrice": 26.0,
    "name": "Keurig Dr Pepper"
  },
  {
    "symbol": "HRL",
    "momentum": -16.16535465988577,
    "currentPrice": 20.65999984741211,
    "name": "Hormel Foods"
  },
  {
    "symbol": "INVH",
    "momentum": -16.33500021944066,
    "currentPrice": 26.280000686645508,
    "name": "Invitation Homes"
  },
  {
    "symbol": "KVUE",
    "momentum": -16.525703264108984,
    "currentPrice": 17.299999237060547,
    "name": "Kenvue"
  },
  {
    "symbol": "TAP",
    "momentum": -17.01684693895685,
    "currentPrice": 44.310001373291016,
    "name": "Molson Coors Beverage Company"
  },
  {
    "symbol": "PGR",
    "momentum": -18.218377030654764,
    "currentPrice": 201.22999572753906,
    "name": "Progressive Corporation"
  },
  {
    "symbol": "CAG",
    "momentum": -18.602899147551785,
    "currentPrice": 14.09000015258789,
    "name": "Conagra Brands"
  },
  {
    "symbol": "BR",
    "momentum": -18.833418931815398,
    "currentPrice": 160.8300018310547,
    "name": "Broadridge Financial Solutions"
  },
  {
    "symbol": "MRSH",
    "momentum": -18.979459453063743,
    "currentPrice": 174.89999389648438,
    "name": "Marsh McLennan"
  },
  {
    "symbol": "GIS",
    "momentum": -19.83835970587026,
    "currentPrice": 34.4900016784668,
    "name": "General Mills"
  },
  {
    "symbol": "ADBE",
    "momentum": -20.648481019235142,
    "currentPrice": 244.66000366210938,
    "name": "Adobe Inc."
  },
  {
    "symbol": "PYPL",
    "momentum": -21.978841418869557,
    "currentPrice": 49.56999969482422,
    "name": "PayPal"
  },
  {
    "symbol": "CRM",
    "momentum": -22.33604047002297,
    "currentPrice": 177.60000610351562,
    "name": "Salesforce"
  },
  {
    "symbol": "KMB",
    "momentum": -22.653376885738368,
    "currentPrice": 96.80999755859375,
    "name": "Kimberly-Clark"
  },
  {
    "symbol": "FICO",
    "momentum": -22.937919801827388,
    "currentPrice": 1030.81005859375,
    "name": "Fair Isaac"
  },
  {
    "symbol": "CMG",
    "momentum": -23.648091334385494,
    "currentPrice": 35.25,
    "name": "Chipotle Mexican Grill"
  },
  {
    "symbol": "BSX",
    "momentum": -24.18897733913632,
    "currentPrice": 64.61000061035156,
    "name": "Boston Scientific"
  },
  {
    "symbol": "INTU",
    "momentum": -24.779909926792367,
    "currentPrice": 389.7200012207031,
    "name": "Intuit"
  },
  {
    "symbol": "ADP",
    "momentum": -24.93482199000547,
    "currentPrice": 196.9199981689453,
    "name": "Automatic Data Processing"
  },
  {
    "symbol": "FIS",
    "momentum": -25.800326298495857,
    "currentPrice": 48.31999969482422,
    "name": "Fidelity National Information Services"
  },
  {
    "symbol": "VRSK",
    "momentum": -25.84274363379992,
    "currentPrice": 176.83999633789062,
    "name": "Verisk Analytics"
  },
  {
    "symbol": "POOL",
    "momentum": -25.952943664987373,
    "currentPrice": 226.58999633789062,
    "name": "Pool Corporation"
  },
  {
    "symbol": "ACN",
    "momentum": -26.009572302132373,
    "currentPrice": 194.0,
    "name": "Accenture"
  },
  {
    "symbol": "ARE",
    "momentum": -27.06569453333771,
    "currentPrice": 47.61000061035156,
    "name": "Alexandria Real Estate Equities"
  },
  {
    "symbol": "CNC",
    "momentum": -27.412065164975814,
    "currentPrice": 37.599998474121094,
    "name": "Centene Corporation"
  },
  {
    "symbol": "NOW",
    "momentum": -28.539150900662346,
    "currentPrice": 94.19000244140625,
    "name": "ServiceNow"
  },
  {
    "symbol": "CPB",
    "momentum": -29.168870579998384,
    "currentPrice": 20.489999771118164,
    "name": "Campbell's Company (The)"
  },
  {
    "symbol": "CHTR",
    "momentum": -30.22556390977444,
    "currentPrice": 220.2899932861328,
    "name": "Charter Communications"
  },
  {
    "symbol": "LULU",
    "momentum": -30.540959174952114,
    "currentPrice": 162.74000549316406,
    "name": "Lululemon Athletica"
  },
  {
    "symbol": "BAX",
    "momentum": -30.661772340296295,
    "currentPrice": 17.600000381469727,
    "name": "Baxter International"
  },
  {
    "symbol": "AJG",
    "momentum": -31.72615043960829,
    "currentPrice": 223.1699981689453,
    "name": "Arthur J. Gallagher & Co."
  },
  {
    "symbol": "PAYX",
    "momentum": -31.875355330557937,
    "currentPrice": 90.26000213623047,
    "name": "Paychex"
  },
  {
    "symbol": "ELV",
    "momentum": -31.994951774616727,
    "currentPrice": 311.17999267578125,
    "name": "Elevance Health"
  },
  {
    "symbol": "ERIE",
    "momentum": -33.017286400550134,
    "currentPrice": 244.52999877929688,
    "name": "Erie Indemnity"
  },
  {
    "symbol": "ROP",
    "momentum": -34.718649842999596,
    "currentPrice": 358.0899963378906,
    "name": "Roper Technologies"
  },
  {
    "symbol": "HUM",
    "momentum": -35.204908678091265,
    "currentPrice": 198.3699951171875,
    "name": "Humana"
  },
  {
    "symbol": "TYL",
    "momentum": -35.32996928246887,
    "currentPrice": 337.6099853515625,
    "name": "Tyler Technologies"
  },
  {
    "symbol": "CPRT",
    "momentum": -36.17092950325055,
    "currentPrice": 33.36000061035156,
    "name": "Copart"
  },
  {
    "symbol": "WDAY",
    "momentum": -37.183264209432785,
    "currentPrice": 124.12000274658203,
    "name": "Workday"
  },
  {
    "symbol": "BRO",
    "momentum": -39.075920307164004,
    "currentPrice": 67.4000015258789,
    "name": "Brown & Brown"
  },
  {
    "symbol": "CSGP",
    "momentum": -39.762084919934324,
    "currentPrice": 39.310001373291016,
    "name": "CoStar Group"
  },
  {
    "symbol": "FDS",
    "momentum": -46.475401383381175,
    "currentPrice": 230.75,
    "name": "FactSet"
  },
  {
    "symbol": "TTD",
    "momentum": -48.04953626430679,
    "currentPrice": 22.3799991607666,
    "name": "Trade Desk (The)"
  },
  {
    "symbol": "GDDY",
    "momentum": -48.513353523021415,
    "currentPrice": 82.33000183105469,
    "name": "GoDaddy"
  },
  {
    "symbol": "UNH",
    "momentum": -49.08434173576622,
    "currentPrice": 314.04998779296875,
    "name": "UnitedHealth Group"
  },
  {
    "symbol": "IT",
    "momentum": -58.5125182451934,
    "currentPrice": 152.38999938964844,
    "name": "Gartner"
  }
]